AiPi/__init__.py
ai_apichat-0.0.2.dist-info/licenses/LICENSE
ai_apichat-0.0.2.dist-info/METADATA
ai_apichat-0.0.2.dist-info/WHEEL
ai_apichat-0.0.2.dist-info/top_level.txt
ai_apichat-0.0.2.dist-info/RECORD
