Metadata-Version: 2.4
Name: AI-APIChat
Version: 0.0.2
Summary: A simple python based language.It can be embedded in python projects
Home-page: https://github.com/xystudio889/AiPi
Author: xystudio
Author-email: 173288240@qq.com
License: MIT
Requires-Python: >=3.6
License-File: LICENSE
Requires-Dist: openai>=0.10.0
Dynamic: author
Dynamic: author-email
Dynamic: description
Dynamic: home-page
Dynamic: license
Dynamic: license-file
Dynamic: requires-dist
Dynamic: requires-python
Dynamic: summary
